{
  "project_info": {
    "project_number": "903785143344",
    "project_id": "jf-app-a7edc",
    "storage_bucket": "jf-app-a7edc.firebasestorage.app"
  },
  "client": [
    {
      "client_info": {
        "mobilesdk_app_id": "1:903785143344:android:fffe9a2f4853494d6be1f5",
        "android_client_info": {
          "package_name": "com.example.jf_app"
        }
      },
      "oauth_client": [],
      "api_key": [
        {
          "current_key": "AIzaSyC-zyg-PtdKJ9VNk08tn3IrHxTqqtiWazs"
        }
      ],
      "services": {
        "appinvite_service": {
          "other_platform_oauth_client": []
        }
      }
    }
  ],
  "configuration_version": "1"
}